mcp_wxdemo_server/__init__.py
mcp_wxdemo_server/testmcp.py
mcp_wxdemo_server-0.1.0.dist-info/METADATA
mcp_wxdemo_server-0.1.0.dist-info/WHEEL
mcp_wxdemo_server-0.1.0.dist-info/entry_points.txt
mcp_wxdemo_server-0.1.0.dist-info/RECORD
