Metadata-Version: 2.4
Name: mcp-wxdemo-server
Version: 0.1.0
Summary: Add your description here
Author-email: WangXiao <wb-wx869082@alibaba-inc.com>
Requires-Python: >=3.10
Requires-Dist: mcp[cli]>=1.7.1
